{
  "numero": null,
  "titulo": "CUANDO ESTABA EN ANGUSTIA",
  "carpeta": "zContemporaneo",
  "tono": null,
  "compas": null,
  "autor": null,
  "compositor": null,
  "copyright": null,
  "ccli": null,
  "tempo": null,
  "referencias_biblicas": [],
  "secciones": [
    {
      "tipo": "estrofa",
      "numero": 1,
      "lineas": [
        "CUANDO ESTABA EN ANGUSTIA",
        "TU ME HICISTE ENSANCHAR",
        "ME LLENASTE DE GOZO",
        "ME INUNDASTE DE PAZ.",
        "MI LAMENTO CAMBIASTE",
        "Y ME HICISTE DANZAR"
      ]
    },
    {
      "tipo": "estrofa",
      "numero": 2,
      "lineas": [
        "MI CILICIO ROMPISTE",
        "Y AHORA PUEDO CANTAR",
        "MI CORAZÓN AGRADECIDO ESTA",
        "POR TU BONDAD SEÑOR SOY LIBRE DE AFLICCIÓN",
        "Y TU PERDÓN Y HIZO NACER EN MI",
        "UNA NUEVA CANCIÓN DESDE MI CORAZÓN"
      ]
    }
  ]
}